pyt/__init__.py
pyt/data/__init__.py
pyt/data/string_utils.py
pyt/data/type_utils.py
pyt/data/api_alignments/align_np_torch copy.py
pyt/data/api_alignments/align_np_torch.py
pyt/data/api_alignments/parse_parameters.py
pyt/data/api_alignments/test_np.py
pyt/data/api_alignments/unified_data.py
pyt/fileio/__init__.py
pyt/fileio/serialization.py
pyt/fileio/handlers/__init__.py
pyt/fileio/handlers/csv_handler.py
pyt/fileio/handlers/image_handler.py
pyt/fileio/handlers/jsonl_handler.py
pyt/fileio/handlers/npy_handler.py
pyt/fileio/handlers/pickle_handler.py
pyt/fileio/handlers/tensor_handler.py
pyt/fileio/handlers/txt_handler.py
pyt/meta/__init__.py
pyt/meta/hash_utils.py
pyt/meta/network_utils.py
pyt/meta/process_utils.py
pyt/meta/time_utils.py
pyt/misc/__init__.py
pyt/misc/dict_database.py
pyt/misc/git_utils.py
pyt/visualization/__init__.py
pyt/visualization/matplotlib_utils.py
pytmlr-0.0.4.dist-info/METADATA
pytmlr-0.0.4.dist-info/WHEEL
pytmlr-0.0.4.dist-info/top_level.txt
pytmlr-0.0.4.dist-info/RECORD
