Metadata-Version: 2.1
Name: pytmlr
Version: 0.0.4
Summary: A useful tool for machine learning research.
Author-email: Zhan Ling <z6ling@ucsd.edu>
Classifier: Programming Language :: Python :: 3
Classifier: License :: OSI Approved :: MIT License
Classifier: Operating System :: OS Independent
Requires-Python: >=3.10
Requires-Dist: mmengine
Requires-Dist: numpy
Requires-Dist: imageio
Requires-Dist: sqlalchemy
Requires-Dist: seaborn
